rqalpha_futu_datasource/__init__.py
rqalpha_futu_datasource/constants.py
rqalpha_futu_datasource/datasource.py
rqalpha_futu_datasource/download.py
rqalpha_futu_datasource/mod_futu_ds.py
rqalpha_futu_datasource/utils.py
rqalpha_futu_datasource-1.2.0.dist-info/METADATA
rqalpha_futu_datasource-1.2.0.dist-info/WHEEL
rqalpha_futu_datasource-1.2.0.dist-info/licenses/LICENSE
rqalpha_futu_datasource-1.2.0.dist-info/RECORD
