Metadata-Version: 2.4
Name: rqalpha-futu-datasource
Version: 1.2.0
Summary: Futu datasource for rqalpha
Author-email: nange <cctonange@gmail.com>
License:                                  Apache License
License-File: LICENSE
Classifier: Intended Audience :: Developers
Classifier: License :: OSI Approved :: Apache Software License
Classifier: Operating System :: OS Independent
Classifier: Programming Language :: Python :: 3
Classifier: Programming Language :: Python :: 3 :: Only
Classifier: Programming Language :: Python :: 3.11
Classifier: Programming Language :: Python :: 3.12
Classifier: Programming Language :: Python :: 3.13
Classifier: Programming Language :: Python :: 3.14
Classifier: Topic :: Software Development :: Libraries
Requires-Python: <4.0,>=3.11
Requires-Dist: futu-api>=9.4.5408
Requires-Dist: rqalpha>=5.6.4.1
